{"6879515326399624773": {"secret": "54521330264471151284", "redirect_uri": "http://localhost:8080/", "friendly_name": "umbrowser", "client_id": "6879515326399624773", "icon": "/static/images/umbrowser.jpg"}, "3914194987395884500": {"secret": "8557841434120157466", "redirect_uri": "http://vm1-chai2.cs.usyd.edu.au:2001/authorized", "friendly_name": "Mneme-Debjanee", "client_id": "3914194987395884500", "icon": "/static/images/icon.svg"}, "1F7a2ef53ab4eDeedFE0CF91BF8fCD46": {"secret": "DecbFFA7b56d1Df2b58AecFde2BB2d7d", "redirect_uri": "http://enterprise.it.usyd.edu.au:8001/authorized", "friendly_name": "log-enterprise", "client_id": "1F7a2ef53ab4eDeedFE0CF91BF8fCD46", "icon": "http://enterprise.it.usyd.edu.au:8001/image/logo.jpg"}, "804E67fD5FccdfFF1baD21bEBb7dCA4A": {"secret": "eCb73f6381Feb11Df87A54796af3169f", "redirect_uri": "http://localhost:8080/", "friendly_name": "activity", "client_id": "804E67fD5FccdfFF1baD21bEBb7dCA4A", "icon": "/static/images/activity.gif"}, "4574298994434706872": {"secret": "2622287655161152331", "redirect_uri": "http://enterprise.it.usyd.edu.au:8000/authorized", "friendly_name": "Mneme-enterprise", "client_id": "4574298994434706872", "icon": "http://enterprise.it.usyd.edu.au:8000/static/images/mneme.jpg"}, "3Df8640E83aAEFB84E85eEBBB4Ed7fE3": {"secret": "934aA03Cfa0A25DCfa12d53a26501A37", "redirect_uri": "http://personislog.appspot.com/authorized", "friendly_name": "aelogger", "client_id": "3Df8640E83aAEFB84E85eEBBB4Ed7fE3", "icon": "http://personislog.appspot.com/image/logo.jpg"}}